ioutil/__init__.py
ioutil/__main__.py
ioutil/_csv.py
ioutil/_file.py
ioutil/_json.py
ioutil/_parquet.py
ioutil/_text.py
ioutil/_toml.py
ioutil-1.0.3.dist-info/LICENSE
ioutil-1.0.3.dist-info/METADATA
ioutil-1.0.3.dist-info/WHEEL
ioutil-1.0.3.dist-info/entry_points.txt
ioutil-1.0.3.dist-info/top_level.txt
ioutil-1.0.3.dist-info/RECORD
