Metadata-Version: 2.1
Name: ioutil
Version: 1.0.3
Summary: To read and write files.
Author-email: srg <srg.code@pm.me>
License: Apache License, Version 2.0
Project-URL: Homepage, https://github.com/codesrg/ioutil
Project-URL: Bug Tracker, https://github.com/codesrg/ioutil/issues
Keywords: io,read,write,file,ioutil
Classifier: Programming Language :: Python :: 3
Classifier: License :: OSI Approved :: Apache Software License
Classifier: Operating System :: OS Independent
Requires-Python: >=3.6
License-File: LICENSE
